hypatia/__init__.py
hypatia/version.py
hypatia/analysis/__init__.py
hypatia/analysis/plots.py
hypatia/analysis/postprocessing.py
hypatia/backend/Build.py
hypatia/backend/StrData.py
hypatia/backend/__init__.py
hypatia/core/__init__.py
hypatia/core/main.py
hypatia/error_log/Checks.py
hypatia/error_log/Exceptions.py
hypatia/error_log/__init__.py
hypatia/examples/__init__.py
hypatia/examples/load_examples.py
hypatia/examples/Operation/__init__.py
hypatia/examples/Operation/config.xlsx
hypatia/examples/Operation/~$config.xlsx
hypatia/examples/Operation/parameters/__init__.py
hypatia/examples/Operation/parameters/parameters_connections.xlsx
hypatia/examples/Operation/parameters/parameters_global.xlsx
hypatia/examples/Operation/parameters/parameters_reg1.xlsx
hypatia/examples/Operation/parameters/parameters_reg2.xlsx
hypatia/examples/Operation/parameters/~$parameters_reg1.xlsx
hypatia/examples/Operation/sets/__init__.py
hypatia/examples/Operation/sets/global.xlsx
hypatia/examples/Operation/sets/reg1.xlsx
hypatia/examples/Operation/sets/reg2.xlsx
hypatia/examples/Planning/__init__.py
hypatia/examples/Planning/config.xlsx
hypatia/examples/Planning/parameters/__init__.py
hypatia/examples/Planning/parameters/parameters_reg1.xlsx
hypatia/examples/Planning/sets/__init__.py
hypatia/examples/Planning/sets/global.xlsx
hypatia/examples/Planning/sets/reg1.xlsx
hypatia/utility/__init__.py
hypatia/utility/constants.py
hypatia/utility/utility.py
hypatia_test-0.1.1.dist-info/LICENSE
hypatia_test-0.1.1.dist-info/METADATA
hypatia_test-0.1.1.dist-info/WHEEL
hypatia_test-0.1.1.dist-info/top_level.txt
hypatia_test-0.1.1.dist-info/RECORD
