Metadata-Version: 2.1
Name: hypatia-test
Version: 0.1.1
Summary: An Operation and Planning Energy System Modelling Framework in Python
Home-page: https://github.com/SESAM-Polimi/hypatia
Author: Negar Namazifard
Author-email: negarnamazifard@gmail.com
License: Apache 2.0
Platform: UNKNOWN
Classifier: Programming Language :: Python :: 3.7
Classifier: Programming Language :: Python :: 3.8
Classifier: Programming Language :: Python :: 3.9
Classifier: Intended Audience :: End Users/Desktop
Classifier: Intended Audience :: Developers
Classifier: Intended Audience :: Science/Research
Classifier: Operating System :: MacOS :: MacOS X
Classifier: Operating System :: Microsoft :: Windows
Classifier: Programming Language :: Python
Classifier: Topic :: Scientific/Engineering
Requires-Python: >.3.7.0
Requires-Dist: pandas (>=1.3.3)
Requires-Dist: numpy (>=1.21.2)
Requires-Dist: xlsxwriter (<=1.3.7)
Requires-Dist: plotly (>=4.12.0)
Requires-Dist: openpyxl (>=3.0.6)
Requires-Dist: IPython (>=7.22.0)
Requires-Dist: cvxopt (>=1.2.7)
